ldbpy.cpython-38-x86_64-linux-gnu.so
ldbpy.libs/libgomp-a34b3233.so.1.0.0
ldbpy-0.0.3.dist-info/WHEEL
ldbpy-0.0.3.dist-info/METADATA
ldbpy-0.0.3.dist-info/RECORD
ldbpy-0.0.3.dist-info/top_level.txt
ldbpy-0.0.3.dist-info/LICENSE
