Metadata-Version: 2.1
Name: ldbpy
Version: 0.0.3
Summary: ldbpy
Author: Ziheng Wang
Author-email: zihengw@stanford.edu
Requires-Python: >=3.7
License-File: LICENSE
